Metadata-Version: 1.1
Name: topaiza
Version: 0.0.4
Summary: Helper package that handles requests and parsing jargain
Home-page: UNKNOWN
Author: firaskoussa
Author-email: firaskoussa@gmail.com
License: MIT
Keywords: requests
Platform: UNKNOWN
Classifier: Development Status :: 5 - Production/Stable
Classifier: Intended Audience :: Education
Classifier: Operating System :: Microsoft :: Windows :: Windows 10
Classifier: License :: OSI Approved :: MIT License
Classifier: Programming Language :: Python :: 3
